softwarelab-2/16CO125-VG2.v
// gate level modelling

module comparator(A,B,C2,C1,C0);

   output C2,C1,C0;                 // C2= (A=B),  C1= (A>B), C0= (A<B)
   input [3:0]A;
   input [3:0]B;   
   wire x0,x1,x2,x3,w4;

   xnor(x0,A[0],B[0]);       
   xnor(x1,A[1],B[1]);
   xnor(x2,A[2],B[2]);
   xnor(x3,A[3],B[3]);

   and(C2,x0,x1,x2,x3);   // C2= x0x1x2x3
   
   not(w4,B[3]);         // w4=B3'
   and(w5,A[3],w4);      // w5=A3w4
   not(w6,B[2]);         // w6=B2'
   and(w7,A[2],w6,x3);   // w7=A2w6x3
   not(w8,B[1]);         // w8=B1'
   and(w9,A[1],w8,x3,x2); // w9=A1w8x3x2
   not(w10,B[0]);         // w10=B0'
   and(w11,A[0],w10,x3,x2,x1);  //w11=A0w10x3x2x1
   or(C1,w5,w7,w9,w11);       // C1=w5w7w9w11

   nor(C0,C2,C1);            // C0= ~(C2 | C1)
endmodule

softwarelab-2/16CO125-V2.v
// Test Bench

`timescale 1ns/1ps
module inp;
     reg [3:0] A;
     reg [3:0] B;
     wire C2,C1,C0;

     comparator mod(.A(A),.B(B),.C2(C2),.C1(C1),.C0(C0));
     initial
     begin
             $dumpfile("16CO132-V2.vcd");
             $dumpvars(0,inp);
             for(A=0; A<16; A=A+1)
                    for(B=0;B<16;B=B+1)
                          #1;
     end
      initial 
        begin
             $monitor("(A=B) %b,(A>B) %b,(A<B) %b",C2,C1,C0);
        end
       initial #5000 $finish;
endmodule

softwarelab-2/16CO132-V2.vcd
$date
	Sun Oct 15 22:50:09 2017
$end
$version
	Icarus Verilog
$end
$timescale
	1ps
$end
$scope module inp $end
$var wire 1 ! C2 $end
$var wire 1 " C1 $end
$var wire 1 # C0 $end
$var reg 4 $ A [3:0] $end
$var reg 4 % B [3:0] $end
$scope module mod $end
$var wire 4 & A [3:0] $end
$var wire 4 ' B [3:0] $end
$var wire 1 # C0 $end
$var wire 1 " C1 $end
$var wire 1 ! C2 $end
$var wire 1 ( w10 $end
$var wire 1 ) w11 $end
$var wire 1 * w4 $end
$var wire 1 + w5 $end
$var wire 1 , w6 $end
$var wire 1 - w7 $end
$var wire 1 . w8 $end
$var wire 1 / w9 $end
$var wire 1 0 x0 $end
$var wire 1 1 x1 $end
$var wire 1 2 x2 $end
$var wire 1 3 x3 $end
$upscope $end
$upscope $end
$enddefinitions $end
#0
$dumpvars
13
12
11
10
0/
1.
0-
1,
0+
1*
0)
1(
b0 '
b0 &
b0 %
b0 $
0#
0"
1!
$end
#1000
1#
0!
00
0(
b1 %
b1 '
#2000
10
01
0.
1(
b10 %
b10 '
#3000
00
0(
b11 %
b11 '
#4000
10
11
02
0,
1.
1(
b100 %
b100 '
#5000
00
0(
b101 %
b101 '
#6000
10
01
0.
1(
b110 %
b110 '
#7000
00
0(
b111 %
b111 '
#8000
10
11
12
03
0*
1,
1.
1(
b1000 %
b1000 '
#9000
00
0(
b1001 %
b1001 '
#10000
10
01
0.
1(
b1010 %
b1010 '
#11000
00
0(
b1011 %
b1011 '
#12000
10
11
02
0,
1.
1(
b1100 %
b1100 '
#13000
00
0(
b1101 %
b1101 '
#14000
10
01
0.
1(
b1110 %
b1110 '
#15000
00
0(
b1111 %
b1111 '
#16000
0#
1!
10
11
12
13
1*
1,
1.
1(
b0 %
b0 '
#17000
1#
0!
00
0(
b1 %
b1 '
#18000
10
01
0.
1(
b10 %
b10 '
#19000
00
0(
b11 %
b11 '
#20000
10
11
02
0,
1.
1(
b100 %
b100 '
#21000
00
0(
b101 %
b101 '
#22000
10
01
0.
1(
b110 %
b110 '
#23000
00
0(
b111 %
b111 '
#24000
10
11
12
03
0*
1,
1.
1(
b1000 %
b1000 '
#25000
00
0(
b1001 %
b1001 '
#26000
10
01
0.
1(
b1010 %
b1010 '
#27000
00
0(
b1011 %
b1011 '
#28000
10
11
02
0,
1.
1(
b1100 %
b1100 '
#29000
00
0(
b1101 %
b1101 '
#30000
10
01
0.
1(
b1110 %
b1110 '
#31000
00
0(
b1111 %
b1111 '
#32000
0#
1!
10
11
12
13
1*
1,
1.
1(
b0 %
b0 '
#33000
1#
0!
00
0(
b1 %
b1 '
#34000
10
01
0.
1(
b10 %
b10 '
#35000
00
0(
b11 %
b11 '
#36000
10
11
02
0,
1.
1(
b100 %
b100 '
#37000
00
0(
b101 %
b101 '
#38000
10
01
0.
1(
b110 %
b110 '
#39000
00
0(
b111 %
b111 '
#40000
10
11
12
03
0*
1,
1.
1(
b1000 %
b1000 '
#41000
00
0(
b1001 %
b1001 '
#42000
10
01
0.
1(
b1010 %
b1010 '
#43000
00
0(
b1011 %
b1011 '
#44000
10
11
02
0,
1.
1(
b1100 %
b1100 '
#45000
00
0(
b1101 %
b1101 '
#46000
10
01
0.
1(
b1110 %
b1110 '
#47000
00
0(
b1111 %
b1111 '
#48000
0#
1!
10
11
12
13
1*
1,
1.
1(
b0 %
b0 '
#49000
1#
0!
00
0(
b1 %
b1 '
#50000
10
01
0.
1(
b10 %
b10 '
#51000
00
0(
b11 %
b11 '
#52000
10
11
02
0,
1.
1(
b100 %
b100 '
#53000
00
0(
b101 %
b101 '
#54000
10
01
0.
1(
b110 %
b110 '
#55000
00
0(
b111 %
b111 '
#56000
10
11
12
03
0*
1,
1.
1(
b1000 %
b1000 '
#57000
00
0(
b1001 %
b1001 '
#58000
10
01
0.
1(
b1010 %
b1010 '
#59000
00
0(
b1011 %
b1011 '
#60000
10
11
02
0,
1.
1(
b1100 %
b1100 '
#61000
00
0(
b1101 %
b1101 '
#62000
10
01
0.
1(
b1110 %
b1110 '
#63000
00
0(
b1111 %
b1111 '
#64000
0#
1!
10
11
12
13
1*
1,
1.
1(
b0 %
b0 '
#65000
1#
0!
00
0(
b1 %
b1 '
#66000
10
01
0.
1(
b10 %
b10 '
#67000
00
0(
b11 %
b11 '
#68000
10
11
02
0,
1.
1(
b100 %
b100 '
#69000
00
0(
b101 %
b101 '
#70000
10
01
0.
1(
b110 %
b110 '
#71000
00
0(
b111 %
b111 '
#72000
10
11
12
03
0*
1,
1.
1(
b1000 %
b1000 '
#73000
00
0(
b1001 %
b1001 '
#74000
10
01
0.
1(
b1010 %
b1010 '
#75000
00
0(
b1011 %
b1011 '
#76000
10
11
02
0,
1.
1(
b1100 %
b1100 '
#77000
00
0(
b1101 %
b1101 '
#78000
10
01
0.
1(
b1110 %
b1110 '
#79000
00
0(
b1111 %
b1111 '
#80000
0#
1!
10
11
12
13
1*
1,
1.
1(
b0 %
b0 '
#81000
1#
0!
00
0(
b1 %
b1 '
#82000
10
01
0.
1(
b10 %
b10 '
#83000
00
0(
b11 %
b11 '
#84000
10
11
02
0,
1.
1(
b100 %
b100 '
#85000
00
0(
b101 %
b101 '
#86000
10
01
0.
1(
b110 %
b110 '
#87000
00
0(
b111 %
b111 '
#88000
10
11
12
03
0*
1,
1.
1(
b1000 %
b1000 '
#89000
00
0(
b1001 %
b1001 '
#90000
10
01
0.
1(
b1010 %
b1010 '
#91000
00
0(
b1011 %
b1011 '
#92000
10
11
02
0,
1.
1(
b1100 %
b1100 '
#93000
00
0(
b1101 %
b1101 '
#94000
10
01
0.
1(
b1110 %
b1110 '
#95000
00
0(
b1111 %
b1111 '
#96000
0#
1!
10
11
12
13
1*
1,
1.
1(
b0 %
b0 '
#97000
1#
0!
00
0(
b1 %
b1 '
#98000
10
01
0.
1(
b10 %
b10 '
#99000
00
0(
b11 %
b11 '
#100000
10
11
02
0,
1.
1(
b100 %
b100 '
#101000
00
0(
b101 %
b101 '
#102000
10
01
0.
1(
b110 %
b110 '
#103000
00
0(
b111 %
b111 '
#104000
10
11
12
03
0*
1,
1.
1(
b1000 %
b1000 '
#105000
00
0(
b1001 %
b1001 '
#106000
10
01
0.
1(
b1010 %
b1010 '
#107000
00
0(
b1011 %
b1011 '
#108000
10
11
02
0,
1.
1(
b1100 %
b1100 '
#109000
00
0(
b1101 %
b1101 '
#110000
10
01
0.
1(
b1110 %
b1110 '
#111000
00
0(
b1111 %
b1111 '
#112000
0#
1!
10
11
12
13
1*
1,
1.
1(
b0 %
b0 '
#113000
1#
0!
00
0(
b1 %
b1 '
#114000
10
01
0.
1(
b10 %
b10 '
#115000
00
0(
b11 %
b11 '
#116000
10
11
02
0,
1.
1(
b100 %
b100 '
#117000
00
0(
b101 %
b101 '
#118000
10
01
0.
1(
b110 %
b110 '
#119000
00
0(
b111 %
b111 '
#120000
10
11
12
03
0*
1,
1.
1(
b1000 %
b1000 '
#121000
00
0(
b1001 %
b1001 '
#122000
10
01
0.
1(
b1010 %
b1010 '
#123000
00
0(
b1011 %
b1011 '
#124000
10
11
02
0,
1.
1(
b1100 %
b1100 '
#125000
00
0(
b1101 %
b1101 '
#126000
10
01
0.
1(
b1110 %
b1110 '
#127000
00
0(
b1111 %
b1111 '
#128000
0#
1!
10
11
12
13
1*
1,
1.
1(
b0 %
b0 '
#129000
1#
0!
00
0(
b1 %
b1 '
#130000
10
01
0.
1(
b10 %
b10 '
#131000
00
0(
b11 %
b11 '
#132000
10
11
02
0,
1.
1(
b100 %
b100 '
#133000
00
0(
b101 %
b101 '
#134000
10
01
0.
1(
b110 %
b110 '
#135000
00
0(
b111 %
b111 '
#136000
10
11
12
03
0*
1,
1.
1(
b1000 %
b1000 '
#137000
00
0(
b1001 %
b1001 '
#138000
10
01
0.
1(
b1010 %
b1010 '
#139000
00
0(
b1011 %
b1011 '
#140000
10
11
02
0,
1.
1(
b1100 %
b1100 '
#141000
00
0(
b1101 %
b1101 '
#142000
10
01
0.
1(
b1110 %
b1110 '
#143000
00
0(
b1111 %
b1111 '
#144000
0#
1!
10
11
12
13
1*
1,
1.
1(
b0 %
b0 '
#145000
1#
0!
00
0(
b1 %
b1 '
#146000
10
01
0.
1(
b10 %
b10 '
#147000
00
0(
b11 %
b11 '
#148000
10
11
02
0,
1.
1(
b100 %
b100 '
#149000
00
0(
b101 %
b101 '
#150000
10
01
0.
1(
b110 %
b110 '
#151000
00
0(
b111 %
b111 '
#152000
10
11
12
03
0*
1,
1.
1(
b1000 %
b1000 '
#153000
00
0(
b1001 %
b1001 '
#154000
10
01
0.
1(
b1010 %
b1010 '
#155000
00
0(
b1011 %
b1011 '
#156000
10
11
02
0,
1.
1(
b1100 %
b1100 '
#157000
00
0(
b1101 %
b1101 '
#158000
10
01
0.
1(
b1110 %
b1110 '
#159000
00
0(
b1111 %
b1111 '
#160000
0#
1!
10
11
12
13
1*
1,
1.
1(
b0 %
b0 '
#161000
1#
0!
00
0(
b1 %
b1 '
#162000
10
01
0.
1(
b10 %
b10 '
#163000
00
0(
b11 %
b11 '
#164000
10
11
02
0,
1.
1(
b100 %
b100 '
#165000
00
0(
b101 %
b101 '
#166000
10
01
0.
1(
b110 %
b110 '
#167000
00
0(
b111 %
b111 '
#168000
10
11
12
03
0*
1,
1.
1(
b1000 %
b1000 '
#169000
00
0(
b1001 %
b1001 '
#170000
10
01
0.
1(
b1010 %
b1010 '
#171000
00
0(
b1011 %
b1011 '
#172000
10
11
02
0,
1.
1(
b1100 %
b1100 '
#173000
00
0(
b1101 %
b1101 '
#174000
10
01
0.
1(
b1110 %
b1110 '
#175000
00
0(
b1111 %
b1111 '
#176000
0#
1!
10
11
12
13
1*
1,
1.
1(
b0 %
b0 '
#177000
1#
0!
00
0(
b1 %
b1 '
#178000
10
01
0.
1(
b10 %
b10 '
#179000
00
0(
b11 %
b11 '
#180000
10
11
02
0,
1.
1(
b100 %
b100 '
#181000
00
0(
b101 %
b101 '
#182000
10
01
0.
1(
b110 %
b110 '
#183000
00
0(
b111 %
b111 '
#184000
10
11
12
03
0*
1,
1.
1(
b1000 %
b1000 '
#185000
00
0(
b1001 %
b1001 '
#186000
10
01
0.
1(
b1010 %
b1010 '
#187000
00
0(
b1011 %
b1011 '
#188000
10
11
02
0,
1.
1(
b1100 %
b1100 '
#189000
00
0(
b1101 %
b1101 '
#190000
10
01
0.
1(
b1110 %
b1110 '
#191000
00
0(
b1111 %
b1111 '
#192000
0#
1!
10
11
12
13
1*
1,
1.
1(
b0 %
b0 '
#193000
1#
0!
00
0(
b1 %
b1 '
#194000
10
01
0.
1(
b10 %
b10 '
#195000
00
0(
b11 %
b11 '
#196000
10
11
02
0,
1.
1(
b100 %
b100 '
#197000
00
0(
b101 %
b101 '
#198000
10
01
0.
1(
b110 %
b110 '
#199000
00
0(
b111 %
b111 '
#200000
10
11
12
03
0*
1,
1.
1(
b1000 %
b1000 '
#201000
00
0(
b1001 %
b1001 '
#202000
10
01
0.
1(
b1010 %
b1010 '
#203000
00
0(
b1011 %
b1011 '
#204000
10
11
02
0,
1.
1(
b1100 %
b1100 '
#205000
00
0(
b1101 %
b1101 '
#206000
10
01
0.
1(
b1110 %
b1110 '
#207000
00
0(
b1111 %
b1111 '
#208000
0#
1!
10
11
12
13
1*
1,
1.
1(
b0 %
b0 '
#209000
1#
0!
00
0(
b1 %
b1 '
#210000
10
01
0.
1(
b10 %
b10 '
#211000
00
0(
b11 %
b11 '
#212000
10
11
02
0,
1.
1(
b100 %
b100 '
#213000
00
0(
b101 %
b101 '
#214000
10
01
0.
1(
b110 %
b110 '
#215000
00
0(
b111 %
b111 '
#216000
10
11
12
03
0*
1,
1.
1(
b1000 %
b1000 '
#217000
00
0(
b1001 %
b1001 '
#218000
10
01
0.
1(
b1010 %
b1010 '
#219000
00
0(
b1011 %
b1011 '
#220000
10
11
02
0,
1.
1(
b1100 %
b1100 '
#221000
00
0(
b1101 %
b1101 '
#222000
10
01
0.
1(
b1110 %
b1110 '
#223000
00
0(
b1111 %
b1111 '
#224000
0#
1!
10
11
12
13
1*
1,
1.
1(
b0 %
b0 '
#225000
1#
0!
00
0(
b1 %
b1 '
#226000
10
01
0.
1(
b10 %
b10 '
#227000
00
0(
b11 %
b11 '
#228000
10
11
02
0,
1.
1(
b100 %
b100 '
#229000
00
0(
b101 %
b101 '
#230000
10
01
0.
1(
b110 %
b110 '
#231000
00
0(
b111 %
b111 '
#232000
10
11
12
03
0*
1,
1.
1(
b1000 %
b1000 '
#233000
00
0(
b1001 %
b1001 '
#234000
10
01
0.
1(
b1010 %
b1010 '
#235000
00
0(
b1011 %
b1011 '
#236000
10
11
02
0,
1.
1(
b1100 %
b1100 '
#237000
00
0(
b1101 %
b1101 '
#238000
10
01
0.
1(
b1110 %
b1110 '
#239000
00
0(
b1111 %
b1111 '
#240000
0#
1!
10
11
12
13
1*
1,
1.
1(
b0 %
b0 '
#241000
1#
0!
00
0(
b1 %
b1 '
#242000
10
01
0.
1(
b10 %
b10 '
#243000
00
0(
b11 %
b11 '
#244000
10
11
02
0,
1.
1(
b100 %
b100 '
#245000
00
0(
b101 %
b101 '
#246000
10
01
0.
1(
b110 %
b110 '
#247000
00
0(
b111 %
b111 '
#248000
10
11
12
03
0*
1,
1.
1(
b1000 %
b1000 '
#249000
00
0(
b1001 %
b1001 '
#250000
10
01
0.
1(
b1010 %
b1010 '
#251000
00
0(
b1011 %
b1011 '
#252000
10
11
02
0,
1.
1(
b1100 %
b1100 '
#253000
00
0(
b1101 %
b1101 '
#254000
10
01
0.
1(
b1110 %
b1110 '
#255000
00
0(
b1111 %
b1111 '
#256000
0#
1!
10
11
12
13
1*
1,
1.
1(
b0 %
b0 '
#257000
1#
0!
00
0(
b1 %
b1 '
#258000
10
01
0.
1(
b10 %
b10 '
#259000
00
0(
b11 %
b11 '
#260000
10
11
02
0,
1.
1(
b100 %
b100 '
#261000
00
0(
b101 %
b101 '
#262000
10
01
0.
1(
b110 %
b110 '
#263000
00
0(
b111 %
b111 '
#264000
10
11
12
03
0*
1,
1.
1(
b1000 %
b1000 '
#265000
00
0(
b1001 %
b1001 '
#266000
10
01
0.
1(
b1010 %
b1010 '
#267000
00
0(
b1011 %
b1011 '
#268000
10
11
02
0,
1.
1(
b1100 %
b1100 '
#269000
00
0(
b1101 %
b1101 '
#270000
10
01
0.
1(
b1110 %
b1110 '
#271000
00
0(
b1111 %
b1111 '
#272000
0#
1!
10
11
12
13
1*
1,
1.
1(
b0 %
b0 '
#273000
1#
0!
00
0(
b1 %
b1 '
#274000
10
01
0.
1(
b10 %
b10 '
#275000
00
0(
b11 %
b11 '
#276000
10
11
02
0,
1.
1(
b100 %
b100 '
#277000
00
0(
b101 %
b101 '
#278000
10
01
0.
1(
b110 %
b110 '
#279000
00
0(
b111 %
b111 '
#280000
10
11
12
03
0*
1,
1.
1(
b1000 %
b1000 '
#281000
00
0(
b1001 %
b1001 '
#282000
10
01
0.
1(
b1010 %
b1010 '
#283000
00
0(
b1011 %
b1011 '
#284000
10
11
02
0,
1.
1(
b1100 %
b1100 '
#285000
00
0(
b1101 %
b1101 '
#286000
10
01
0.
1(
b1110 %
b1110 '
#287000
00
0(
b1111 %
b1111 '
#288000
0#
1!
10
11
12
13
1*
1,
1.
1(
b0 %
b0 '
#289000
1#
0!
00
0(
b1 %
b1 '
#290000
10
01
0.
1(
b10 %
b10 '
#291000
00
0(
b11 %
b11 '
#292000
10
11
02
0,
1.
1(
b100 %
b100 '
#293000
00
0(
b101 %
b101 '
#294000
10
01
0.
1(
b110 %
b110 '
#295000
00
0(
b111 %
b111 '
#296000
10
11
12
03
0*
1,
1.
1(
b1000 %
b1000 '
#297000
00
0(
b1001 %
b1001 '
#298000
10
01
0.
1(
b1010 %
b1010 '
#299000
00
0(
b1011 %
b1011 '
#300000
10
11
02
0,
1.
1(
b1100 %
b1100 '
#301000
00
0(
b1101 %
b1101 '
#302000
10
01
0.
1(
b1110 %
b1110 '
#303000
00
0(
b1111 %
b1111 '
#304000
0#
1!
10
11
12
13
1*
1,
1.
1(
b0 %
b0 '
#305000
1#
0!
00
0(
b1 %
b1 '
#306000
10
01
0.
1(
b10 %
b10 '
#307000
00
0(
b11 %
b11 '
#308000
10
11
02
0,
1.
1(
b100 %
b100 '
#309000
00
0(
b101 %
b101 '
#310000
10
01
0.
1(
b110 %
b110 '
#311000
00
0(
b111 %
b111 '
#312000
10
11
12
03
0*
1,
1.
1(
b1000 %
b1000 '
#313000
00
0(
b1001 %
b1001 '
#314000
10
01
0.
1(
b1010 %
b1010 '
#315000
00
0(
b1011 %
b1011 '
#316000
10
11
02
0,
1.
1(
b1100 %
b1100 '
#317000
00
0(
b1101 %
b1101 '
#318000
10
01
0.
1(
b1110 %
b1110 '
#319000
00
0(
b1111 %
b1111 '
#320000
0#
1!
10
11
12
13
1*
1,
1.
1(
b0 %
b0 '
#321000
1#
0!
00
0(
b1 %
b1 '
#322000
10
01
0.
1(
b10 %
b10 '
#323000
00
0(
b11 %
b11 '
#324000
10
11
02
0,
1.
1(
b100 %
b100 '
#325000
00
0(
b101 %
b101 '
#326000
10
01
0.
1(
b110 %
b110 '
#327000
00
0(
b111 %
b111 '
#328000
10
11
12
03
0*
1,
1.
1(
b1000 %
b1000 '
#329000
00
0(
b1001 %
b1001 '
#330000
10
01
0.
1(
b1010 %
b1010 '
#331000
00
0(
b1011 %
b1011 '
#332000
10
11
02
0,
1.
1(
b1100 %
b1100 '
#333000
00
0(
b1101 %
b1101 '
#334000
10
01
0.
1(
b1110 %
b1110 '
#335000
00
0(
b1111 %
b1111 '
#336000
0#
1!
10
11
12
13
1*
1,
1.
1(
b0 %
b0 '
#337000
1#
0!
00
0(
b1 %
b1 '
#338000
10
01
0.
1(
b10 %
b10 '
#339000
00
0(
b11 %
b11 '
#340000
10
11
02
0,
1.
1(
b100 %
b100 '
#341000
00
0(
b101 %
b101 '
#342000
10
01
0.
1(
b110 %
b110 '
#343000
00
0(
b111 %
b111 '
#344000
10
11
12
03
0*
1,
1.
1(
b1000 %
b1000 '
#345000
00
0(
b1001 %
b1001 '
#346000
10
01
0.
1(
b1010 %
b1010 '
#347000
00
0(
b1011 %
b1011 '
#348000
10
11
02
0,
1.
1(
b1100 %
b1100 '
#349000
00
0(
b1101 %
b1101 '
#350000
10
01
0.
1(
b1110 %
b1110 '
#351000
00
0(
b1111 %
b1111 '
#352000
0#
1!
10
11
12
13
1*
1,
1.
1(
b0 %
b0 '
#353000
1#
0!
00
0(
b1 %
b1 '
#354000
10
01
0.
1(
b10 %
b10 '
#355000
00
0(
b11 %
b11 '
#356000
10
11
02
0,
1.
1(
b100 %
b100 '
#357000
00
0(
b101 %
b101 '
#358000
10
01
0.
1(
b110 %
b110 '
#359000
00
0(
b111 %
b111 '
#360000
10
11
12
03
0*
1,
1.
1(
b1000 %
b1000 '
#361000
00
0(
b1001 %
b1001 '
#362000
10
01
0.
1(
b1010 %
b1010 '
#363000
00
0(
b1011 %
b1011 '
#364000
10
11
02
0,
1.
1(
b1100 %
b1100 '
#365000
00
0(
b1101 %
b1101 '
#366000
10
01
0.
1(
b1110 %
b1110 '
#367000
00
0(
b1111 %
b1111 '
#368000
0#
1!
10
11
12
13
1*
1,
1.
1(
b0 %
b0 '
#369000
1#
0!
00
0(
b1 %
b1 '
#370000
10
01
0.
1(
b10 %
b10 '
#371000
00
0(
b11 %
b11 '
#372000
10
11
02
0,
1.
1(
b100 %
b100 '
#373000
00
0(
b101 %
b101 '
#374000
10
01
0.
1(
b110 %
b110 '
#375000
00
0(
b111 %
b111 '
#376000
10
11
12
03
0*
1,
1.
1(
b1000 %
b1000 '
#377000
00
0(
b1001 %
b1001 '
#378000
10
01
0.
1(
b1010 %
b1010 '
#379000
00
0(
b1011 %
b1011 '
#380000
10
11
02
0,
1.
1(
b1100 %
b1100 '
#381000
00
0(
b1101 %
b1101 '
#382000
10
01
0.
1(
b1110 %
b1110 '
#383000
00
0(
b1111 %
b1111 '
#384000
0#
1!
10
11
12
13
1*
1,
1.
1(
b0 %
b0 '
#385000
1#
0!
00
0(
b1 %
b1 '
#386000
10
01
0.
1(
b10 %
b10 '
#387000
00
0(
b11 %
b11 '
#388000
10
11
02
0,
1.
1(
b100 %
b100 '
#389000
00
0(
b101 %
b101 '
#390000
10
01
0.
1(
b110 %
b110 '
#391000
00
0(
b111 %
b111 '
#392000
10
11
12
03
0*
1,
1.
1(
b1000 %
b1000 '
#393000
00
0(
b1001 %
b1001 '
#394000
10
01
0.
1(
b1010 %
b1010 '
#395000
00
0(
b1011 %
b1011 '
#396000
10
11
02
0,
1.
1(
b1100 %
b1100 '
#397000
00
0(
b1101 %
b1101 '
#398000
10
01
0.
1(
b1110 %
b1110 '
#399000
00
0(
b1111 %
b1111 '
#400000
0#
1!
10
11
12
13
1*
1,
1.
1(
b0 %
b0 '
#401000
1#
0!
00
0(
b1 %
b1 '
#402000
10
01
0.
1(
b10 %
b10 '
#403000
00
0(
b11 %
b11 '
#404000
10
11
02
0,
1.
1(
b100 %
b100 '
#405000
00
0(
b101 %
b101 '
#406000
10
01
0.
1(
b110 %
b110 '
#407000
00
0(
b111 %
b111 '
#408000
10
11
12
03
0*
1,
1.
1(
b1000 %
b1000 '
#409000
00
0(
b1001 %
b1001 '
#410000
10
01
0.
1(
b1010 %
b1010 '
#411000
00
0(
b1011 %
b1011 '
#412000
10
11
02
0,
1.
1(
b1100 %
b1100 '
#413000
00
0(
b1101 %
b1101 '
#414000
10
01
0.
1(
b1110 %
b1110 '
#415000
00
0(
b1111 %
b1111 '
#416000
0#
1!
10
11
12
13
1*
1,
1.
1(
b0 %
b0 '
#417000
1#
0!
00
0(
b1 %
b1 '
#418000
10
01
0.
1(
b10 %
b10 '
#419000
00
0(
b11 %
b11 '
#420000
10
11
02
0,
1.
1(
b100 %
b100 '
#421000
00
0(
b101 %
b101 '
#422000
10
01
0.
1(
b110 %
b110 '
#423000
00
0(
b111 %
b111 '
#424000
10
11
12
03
0*
1,
1.
1(
b1000 %
b1000 '
#425000
00
0(
b1001 %
b1001 '
#426000
10
01
0.
1(
b1010 %
b1010 '
#427000
00
0(
b1011 %
b1011 '
#428000
10
11
02
0,
1.
1(
b1100 %
b1100 '
#429000
00
0(
b1101 %
b1101 '
#430000
10
01
0.
1(
b1110 %
b1110 '
#431000
00
0(
b1111 %
b1111 '
#432000
0#
1!
10
11
12
13
1*
1,
1.
1(
b0 %
b0 '
#433000
1#
0!
00
0(
b1 %
b1 '
#434000
10
01
0.
1(
b10 %
b10 '
#435000
00
0(
b11 %
b11 '
#436000
10
11
02
0,
1.
1(
b100 %
b100 '
#437000
00
0(
b101 %
b101 '
#438000
10
01
0.
1(
b110 %
b110 '
#439000
00
0(
b111 %
b111 '
#440000
10
11
12
03
0*
1,
1.
1(
b1000 %
b1000 '
#441000
00
0(
b1001 %
b1001 '
#442000
10
01
0.
1(
b1010 %
b1010 '
#443000
00
0(
b1011 %
b1011 '
#444000
10
11
02
0,
1.
1(
b1100 %
b1100 '
#445000
00
0(
b1101 %
b1101 '
#446000
10
01
0.
1(
b1110 %
b1110 '
#447000
00
0(
b1111 %
b1111 '
#448000
0#
1!
10
11
12
13
1*
1,
1.
1(
b0 %
b0 '
#449000
1#
0!
00
0(
b1 %
b1 '
#450000
10
01
0.
1(
b10 %
b10 '
#451000
00
0(
b11 %
b11 '
#452000
10
11
02
0,
1.
1(
b100 %
b100 '
#453000
00
0(
b101 %
b101 '
#454000
10
01
0.
1(
b110 %
b110 '
#455000
00
0(
b111 %
b111 '
#456000
10
11
12
03
0*
1,
1.
1(
b1000 %
b1000 '
#457000
00
0(
b1001 %
b1001 '
#458000
10
01
0.
1(
b1010 %
b1010 '
#459000
00
0(
b1011 %
b1011 '
#460000
10
11
02
0,
1.
1(
b1100 %
b1100 '
#461000
00
0(
b1101 %
b1101 '
#462000
10
01
0.
1(
b1110 %
b1110 '
#463000
00
0(
b1111 %
b1111 '
#464000
0#
1!
10
11
12
13
1*
1,
1.
1(
b0 %
b0 '
#465000
1#
0!
00
0(
b1 %
b1 '
#466000
10
01
0.
1(
b10 %
b10 '
#467000
00
0(
b11 %
b11 '
#468000
10
11
02
0,
1.
1(
b100 %
b100 '
#469000
00
0(
b101 %
b101 '
#470000
10
01
0.
1(
b110 %
b110 '
#471000
00
0(
b111 %
b111 '
#472000
10
11
12
03
0*
1,
1.
1(
b1000 %
b1000 '
#473000
00
0(
b1001 %
b1001 '
#474000
10
01
0.
1(
b1010 %
b1010 '
#475000
00
0(
b1011 %
b1011 '
#476000
10
11
02
0,
1.
1(
b1100 %
b1100 '
#477000
00
0(
b1101 %
b1101 '
#478000
10
01
0.
1(
b1110 %
b1110 '
#479000
00
0(
b1111 %
b1111 '
#480000
0#
1!
10
11
12
13
1*
1,
1.
1(
b0 %
b0 '
#481000
1#
0!
00
0(
b1 %
b1 '
#482000
10
01
0.
1(
b10 %
b10 '
#483000
00
0(
b11 %
b11 '
#484000
10
11
02
0,
1.
1(
b100 %
b100 '
#485000
00
0(
b101 %
b101 '
#486000
10
01
0.
1(
b110 %
b110 '
#487000
00
0(
b111 %
b111 '
#488000
10
11
12
03
0*
1,
1.
1(
b1000 %
b1000 '
#489000
00
0(
b1001 %
b1001 '
#490000
10
01
0.
1(
b1010 %
b1010 '
#491000
00
0(
b1011 %
b1011 '
#492000
10
11
02
0,
1.
1(
b1100 %
b1100 '
#493000
00
0(
b1101 %
b1101 '
#494000
10
01
0.
1(
b1110 %
b1110 '
#495000
00
0(
b1111 %
b1111 '
#496000
0#
1!
10
11
12
13
1*
1,
1.
1(
b0 %
b0 '
#497000
1#
0!
00
0(
b1 %
b1 '
#498000
10
01
0.
1(
b10 %
b10 '
#499000
00
0(
b11 %
b11 '
#500000
10
11
02
0,
1.
1(
b100 %
b100 '
#501000
00
0(
b101 %
b101 '
#502000
10
01
0.
1(
b110 %
b110 '
#503000
00
0(
b111 %
b111 '
#504000
10
11
12
03
0*
1,
1.
1(
b1000 %
b1000 '
#505000
00
0(
b1001 %
b1001 '
#506000
10
01
0.
1(
b1010 %
b1010 '
#507000
00
0(
b1011 %
b1011 '
#508000
10
11
02
0,
1.
1(
b1100 %
b1100 '
#509000
00
0(
b1101 %
b1101 '
#510000
10
01
0.
1(
b1110 %
b1110 '
#511000
00
0(
b1111 %
b1111 '
#512000
0#
1!
10
11
12
13
1*
1,
1.
1(
b0 %
b0 '
#513000
1#
0!
00
0(
b1 %
b1 '
#514000
10
01
0.
1(
b10 %
b10 '
#515000
00
0(
b11 %
b11 '
#516000
10
11
02
0,
1.
1(
b100 %
b100 '
#517000
00
0(
b101 %
b101 '
#518000
10
01
0.
1(
b110 %
b110 '
#519000
00
0(
b111 %
b111 '
#520000
10
11
12
03
0*
1,
1.
1(
b1000 %
b1000 '
#521000
00
0(
b1001 %
b1001 '
#522000
10
01
0.
1(
b1010 %
b1010 '
#523000
00
0(
b1011 %
b1011 '
#524000
10
11
02
0,
1.
1(
b1100 %
b1100 '
#525000
00
0(
b1101 %
b1101 '
#526000
10
01
0.
1(
b1110 %
b1110 '
#527000
00
0(
b1111 %
b1111 '
#528000
0#
1!
10
11
12
13
1*
1,
1.
1(
b0 %
b0 '
#529000
1#
0!
00
0(
b1 %
b1 '
#530000
10
01
0.
1(
b10 %
b10 '
#531000
00
0(
b11 %
b11 '
#532000
10
11
02
0,
1.
1(
b100 %
b100 '
#533000
00
0(
b101 %
b101 '
#534000
10
01
0.
1(
b110 %
b110 '
#535000
00
0(
b111 %
b111 '
#536000
10
11
12
03
0*
1,
1.
1(
b1000 %
b1000 '
#537000
00
0(
b1001 %
b1001 '
#538000
10
01
0.
1(
b1010 %
b1010 '
#539000
00
0(
b1011 %
b1011 '
#540000
10
11
02
0,
1.
1(
b1100 %
b1100 '
#541000
00
0(
b1101 %
b1101 '
#542000
10
01
0.
1(
b1110 %
b1110 '
#543000
00
0(
b1111 %
b1111 '
#544000
0#
1!
10
11
12
13
1*
1,
1.
1(
b0 %
b0 '
#545000
1#
0!
00
0(
b1 %
b1 '
