softwarelab-4/16CO125-VD4.v
/*
	Generate Binary Sequence using T-FlipFlop : 0,8,5,3,7,2
	Dataflow Modelling
	16CO125
*/
module sequence_generator(Yt,Yt1,clock);
	
	input clock;
	output [3:0]Yt,Yt1;
	output w0,w1,w2,w3;
	tflipflop a3(.Yt(w3),.Yt1(Yt[3]),.clock(clock));
	tflipflop a2(.Yt(w2),.Yt1(Yt[2]),.clock(clock));
	tflipflop a1(.Yt(w1),.Yt1(Yt[1]),.clock(clock));
	tflipflop a0(.Yt(w0),.Yt1(Yt[0]),.clock(clock));
	
	assign w3=((~Yt[0])&(~Yt[1]));
	assign w2=(Yt[3] | Yt[0]);
	assign w1=(Yt[1]^Yt[0]);
	assign w0= (Yt[3] | (Yt[2]&Yt[1]));
	
endmodule

module tflipflop(Yt,Yt1,clock);
	input Yt;
	input clock;
	output Yt1;
	reg Yt1,Yt1c;
	initial begin
		Yt1=0;
		Yt1c=1;
	end
	always @(posedge clock)
	begin
		if(Yt==1'b1) 
			begin
				Yt1=(~Yt1);
				Yt1c=(~Yt1c);
			end
		else if(Yt==1'b0)
			begin
				Yt1=Yt1;
				Yt1c=Yt1c;
			end
	end
endmodule

softwarelab-4/16CO125-V4.v
/*
	Generate Binary Sequence using T-FlipFlop : 0,8,5,3,7,2
	TestBench
	16CO125
*/
`timescale 1ns/1ps
module testbench;
	reg clock;
	wire[3:0] Yt,Yt1;
	sequence_generator f(Yt,Yt1,clock);
	initial begin
		$dumpfile("16CO125-V4.vcd");
		$dumpvars(0,testbench);
	end

	initial begin
		clock=1'b0;
		repeat(60)
			#2 clock=~clock;	
	end
	
	initial begin
		$monitor("clock=%b , count=%d",clock,Yt);
	end
	initial #200 $finish;
endmodule

softwarelab-4/16CO125-V4.vcd
$date
	Thu Nov 02 20:17:04 2017
$end
$version
	Icarus Verilog
$end
$timescale
	1ps
$end
$scope module testbench $end
$var wire 4 ! Yt1 [3:0] $end
$var wire 4 " Yt [3:0] $end
$var reg 1 # clock $end
$scope module f $end
$var wire 1 # clock $end
$var reg 4 $ Yt [3:0] $end
$var reg 4 % Yt1 [3:0] $end
$upscope $end
$upscope $end
$enddefinitions $end
#0
$dumpvars
bx %
b10 $
0#
b10 "
bx !
$end
#2000
b0 "
b0 $
b0 !
b0 %
1#
#4000
0#
#6000
b1000 "
b1000 $
b1000 !
b1000 %
1#
#8000
0#
#10000
b101 "
b101 $
b101 !
b101 %
1#
#12000
0#
#14000
b11 "
b11 $
b11 !
b11 %
1#
#16000
0#
#18000
b111 "
b111 $
b111 !
b111 %
1#
#20000
0#
#22000
b10 "
b10 $
b10 !
b10 %
1#
#24000
0#
#26000
b0 "
b0 $
b0 !
b0 %
1#
#28000
0#
#30000
b1000 "
b1000 $
b1000 !
b1000 %
1#
#32000
0#
#34000
b101 "
b101 $
b101 !
b101 %
1#
#36000
0#
#38000
b11 "
b11 $
b11 !
b11 %
1#
#40000
0#
#42000
b111 "
b111 $
b111 !
b111 %
1#
#44000
0#
#46000
b10 "
b10 $
b10 !
b10 %
1#
#48000
0#
#50000
b0 "
b0 $
b0 !
b0 %
1#
#52000
0#
#54000
b1000 "
b1000 $
b1000 !
b1000 %
1#
#56000
0#
#58000
b101 "
b101 $
b101 !
b101 %
1#
#60000
0#
#62000
b11 "
b11 $
b11 !
b11 %
1#
#64000
0#
#66000
b111 "
b111 $
b111 !
b111 %
1#
#68000
0#
#70000
b10 "
b10 $
b10 !
b10 %
1#
#72000
0#
#74000
b0 "
b0 $
b0 !
b0 %
1#
#76000
0#
#78000
b1000 "
b1000 $
b1000 !
b1000 %
1#
#80000
0#
#82000
b101 "
b101 $
b101 !
b101 %
1#
#84000
0#
#86000
b11 "
b11 $
b11 !
b11 %
1#
#88000
0#
#90000
b111 "
b111 $
b111 !
b111 %
1#
#92000
0#
#94000
b10 "
b10 $
b10 !
b10 %
1#
#96000
0#
#98000
b0 "
b0 $
b0 !
b0 %
1#
#100000
0#
#102000
b1000 "
b1000 $
b1000 !
b1000 %
1#
#104000
0#
#106000
b101 "
b101 $
b101 !
b101 %
1#
#108000
0#
#110000
b11 "
b11 $
b11 !
b11 %
1#
#112000
0#
#114000
b111 "
b111 $
b111 !
b111 %
1#
#116000
0#
#118000
b10 "
b10 $
b10 !
b10 %
1#
