softwarelab-5/16CO125-VG5.v
/*
	PIPO Shift Register
	Gate Modelling
	16CO125
*/
module pipo(data,dataout,clock,reset);
	input reset,clock;
	input[3:0] data;
	output[3:0] dataout;

	d_flip_flop o0(data[0],clock,reset,dataout[0]);
	d_flip_flop o1(data[1],clock,reset,dataout[1]);
	d_flip_flop o2(data[2],clock,reset,dataout[2]);
	d_flip_flop o3(data[3],clock,reset,dataout[3]);

endmodule

module d_flip_flop(d,clock,reset,q);
    output q;
    input d,clock,reset;
    wire dn,resetn,clockn,w1,w2,w3,w4,w1n,w2n,w3n,w4n;

	nand (w1,d,clock);
    not (dn,d);
	nand (w1n,dn,clock);
	not (resetn,reset);
    nand (w2,w1,w2n);
	nand (w2n,resetn,w1n,w2);
	not (clockn,clock);
	nand (w3,clockn,w2);
	nand (w3n,clockn,w2n);
    nand (w4,w4n,w3);
    nand (w4n,w4,w3n);
    buf (q,w4);
   
endmodule

softwarelab-5/16CO125-V5.v
/*
	PIPO Shift Register
	TestBench
	16CO125
*/
`timescale 1ns/1ps
module testbench;
	reg[3:0] data;
	wire[3:0] dataout;
	reg clock,reset;
	
	pipo f1(data,dataout,clock,reset);
	initial begin
		$dumpfile("16CO125-V5.vcd");
		$dumpvars(0,testbench);
	end
	
	always
		begin
			#10 clock=~clock;
		end
	
	initial begin
		$monitor("clock=%b  data=%b  dataout=%b",clock,data,dataout);
	end
	initial begin
		reset=0;
		clock=1;
		data=4'b0000;
		
		#20
			data=4'b0001;
		#20
			data=4'b0010;
		#20
			data=4'b0011;
		#20
			data=4'b0100;
		#20
			data=4'b0101;
		#20
			data=4'b0110;
		#20
			data=4'b0111;		
		#20
			data=4'b1000;
		#20
			data=4'b1001;
		#20
			data=4'b1010;
		#20
			data=4'b1011;
		#20
			data=4'b1100;
		#20
			data=4'b1110;
		#20
			data=4'b1111;
		
		$finish;
	end
endmodule

softwarelab-5/16CO125-V5.vcd
$date
	Sat Nov  4 03:09:02 2017
$end
$version
	Icarus Verilog
$end
$timescale
	1ps
$end
$scope module testbench $end
$var wire 4 ! dataout [3:0] $end
$var reg 1 " clock $end
$var reg 4 # data [3:0] $end
$var reg 1 $ reset $end
$scope module f1 $end
$var wire 1 % clock $end
$var wire 4 & data [3:0] $end
$var wire 1 ' reset $end
$var reg 4 ( dataout [3:0] $end
$upscope $end
$upscope $end
$enddefinitions $end
#0
$dumpvars
bx (
0'
b0 &
1%
0$
b0 #
1"
bx !
$end
#10000
b0 (
b0 !
0"
0%
#20000
1"
1%
b1 #
b1 &
#30000
b1 (
b1 !
0"
0%
#40000
1"
1%
b10 #
b10 &
#50000
b10 (
b10 !
0"
0%
#60000
1"
1%
b11 #
b11 &
#70000
b11 (
b11 !
0"
0%
#80000
1"
1%
b100 #
b100 &
#90000
b100 (
b100 !
0"
0%
#100000
1"
1%
b101 #
b101 &
#110000
b101 (
b101 !
0"
0%
#120000
1"
1%
b110 #
b110 &
#130000
b110 (
b110 !
0"
0%
#140000
1"
1%
b111 #
b111 &
#150000
b111 (
b111 !
0"
0%
#160000
1"
1%
b1000 #
b1000 &
#170000
b1000 (
b1000 !
0"
0%
#180000
1"
1%
b1001 #
b1001 &
#190000
b1001 (
b1001 !
0"
0%
#200000
1"
1%
b1010 #
b1010 &
#210000
b1010 (
b1010 !
0"
0%
#220000
1"
1%
b1011 #
b1011 &
#230000
b1011 (
b1011 !
0"
0%
#240000
1"
1%
b1100 #
b1100 &
#250000
b1100 (
b1100 !
0"
0%
#260000
1"
1%
b1110 #
b1110 &
#270000
b1110 (
b1110 !
0"
0%
#280000
1"
1%
b1111 #
b1111 &
