softwarelab-1/16CO125-VD1.v
// data flow modelling

module complement(a,b,c,d,w,x,y,z);
	input a,b,c,d;
	output w,x,y,z;
	wire w1,w2,w3,w4;	
	
	assign w1 = ~a;
	assign w2 = ~b;
	assign w3 = w1&w2;
	assign w4 = ~c;
	assign w = w3&w4;
	assign x = b^c;
	assign y = c;
	assign z= ~d;

endmodule

softwarelab-1/16CO125-V1.v
`timescale 1ns/1ps
module inp;
	reg a,b,c,d;
	wire w,x,y,z;
	complement out(.a(a),.b(b),.c(c),.d(d),.w(w),.x(x),.y(y),.z(z));
	
	initial
	begin
		$monitor("w x y z\n");
		$dumpfile("16CO125-V1.vcd");
		$dumpvars(0, inp);

		
		a=1'b0;
		b=1'b0;
		c=1'b0;
		d=1'b0;
		$monitor(w,x,y,z,"\n");
		
#10;
		a=1'b0;
		b=1'b0;
		c=1'b0;
		d=1'b1;
		$monitor(w,x,y,z,"\n");

#10;
		a=1'b0;
		b=1'b0;
		c=1'b1;
		d=1'b0;
		$monitor(w,x,y,z,"\n");

#10;		
		a=1'b0;
		b=1'b0;
		c=1'b1;
		d=1'b1;
		$monitor(w,x,y,z,"\n");

#10;		
		a=1'b0;
		b=1'b1;
		c=1'b0;
		d=1'b0;
		$monitor(w,x,y,z,"\n");

#10;
		a=1'b0;
		b=1'b1;
		c=1'b0;
		d=1'b1;
		$monitor(w,x,y,z,"\n");

#10;
		a=1'b0;
		b=1'b1;
		c=1'b1;
		d=1'b0;
		$monitor(w,x,y,z,"\n");

#10;
		a=1'b0;
		b=1'b1;
		c=1'b1;
		d=1'b1;
		$monitor(w,x,y,z,"\n");

#10;
		a=1'b1;
		b=1'b0;
		c=1'b0;
		d=1'b0;
		$monitor(w,x,y,z,"\n");

#10;
		a=1'b1;
		b=1'b0;
		c=1'b0;
		d=1'b1;
		$monitor(w,x,y,z,"\n");
	end
	initial #300 $finish;
endmodule

softwarelab-1/16CO125-V1.vcd
$date
	Thu Sep 21 06:53:19 2017
$end
$version
	Icarus Verilog
$end
$timescale
	1ps
$end
$scope module inp $end
$var wire 1 ! w $end
$var wire 1 " x $end
$var wire 1 # y $end
$var wire 1 $ z $end
$var reg 1 % a $end
$var reg 1 & b $end
$var reg 1 ' c $end
$var reg 1 ( d $end
$scope module out $end
$var wire 1 ) a $end
$var wire 1 * b $end
$var wire 1 + c $end
$var wire 1 , d $end
$var wire 1 ! w $end
$var wire 1 - w1 $end
$var wire 1 . w2 $end
$var wire 1 / w3 $end
$var wire 1 0 w4 $end
$var wire 1 " x $end
$var wire 1 # y $end
$var wire 1 $ z $end
$upscope $end
$upscope $end
$enddefinitions $end
#0
$dumpvars
10
1/
1.
1-
0,
0+
0*
0)
0(
0'
0&
0%
1$
0#
0"
1!
$end
#10000
0$
1(
1,
#20000
0!
1$
00
1"
0(
0,
1'
1#
1+
#30000
0$
1(
1,
#40000
0/
1$
10
0.
0(
0,
0'
0#
0+
1&
1*
#50000
0$
1(
1,
#60000
1$
00
0"
0(
0,
1'
1#
1+
#70000
0$
1(
1,
#80000
1$
10
1.
0-
0(
0,
0'
0#
0+
0&
0*
1%
1)
#90000
0$
1(
1,
